LICENSE
README.md
pyproject.toml
setup.py
src/PowDevLif.egg-info/PKG-INFO
src/PowDevLif.egg-info/SOURCES.txt
src/PowDevLif.egg-info/dependency_links.txt
src/PowDevLif.egg-info/requires.txt
src/PowDevLif.egg-info/top_level.txt
src/powdevlif/__init__.py
src/powdevlif/lifetime.py
src/powdevlif/function/__init__.py
src/powdevlif/function/counters.py
src/powdevlif/function/cumul_endommagement.py
src/powdevlif/function/graphs.py
src/powdevlif/function/losses.py
src/powdevlif/function/materials.py
src/powdevlif/function/matrix.py
src/powdevlif/function/path_reader.py
src/powdevlif/function/poly_somme.py
src/powdevlif/function/temperature.py
src/powdevlif/function/zth_materials.py