Metadata-Version: 2.1
Name: PowDevLif
Version: 0.0.7
Summary: The project aims to assess the lifetime and efficiency of electronic components by using thermal and electrical calculations based on data from an Excel file. Authors: Paul Garnier (paul.garnier@ens-rennes.fr), Briac Baudais (briac.baudais@ens-rennes.fr)
Home-page: https://github.com/PGarn/LifeTime
Author: Garnier Paul, Baudais Briac
Author-email: paul.garnier@ens-rennes.fr, briac.baudais@ens-rennes.fr
License: MIT
Classifier: Development Status :: 3 - Alpha
Classifier: Intended Audience :: Developers
Classifier: License :: OSI Approved :: MIT License
Classifier: Programming Language :: Python :: 3.6
License-File: LICENSE
